{"errors":[],"warnings":[],"namedChunkGroups":{"polyfill":{"chunks":[1,5],"assets":["webpack-runtime-fe393dffc218fde4a454.js","webpack-runtime-fe393dffc218fde4a454.js.map","polyfill-b26ca15045427b9506aa.js","polyfill-b26ca15045427b9506aa.js.map"],"children":{},"childAssets":{}},"app":{"chunks":[1,0,4,2],"assets":["webpack-runtime-fe393dffc218fde4a454.js","webpack-runtime-fe393dffc218fde4a454.js.map","styles.379f2aec5aa6ee65c9e1.css","styles-407fe62976dc5310c43e.js","styles-407fe62976dc5310c43e.js.map","framework-06f646d936b841f99ebd.js","framework-06f646d936b841f99ebd.js.map","app-552e46462e7fd40d34b9.js","app-552e46462e7fd40d34b9.js.map"],"children":{},"childAssets":{}},"component---src-pages-index-js":{"chunks":[0,3],"assets":["styles.379f2aec5aa6ee65c9e1.css","styles-407fe62976dc5310c43e.js","styles-407fe62976dc5310c43e.js.map","component---src-pages-index-js-5edc4f3dc8203913b1fc.js","component---src-pages-index-js-5edc4f3dc8203913b1fc.js.map"],"children":{},"childAssets":{}}},"assetsByChunkName":{"polyfill":["webpack-runtime-fe393dffc218fde4a454.js","polyfill-b26ca15045427b9506aa.js"],"app":["webpack-runtime-fe393dffc218fde4a454.js","styles.379f2aec5aa6ee65c9e1.css","styles-407fe62976dc5310c43e.js","framework-06f646d936b841f99ebd.js","app-552e46462e7fd40d34b9.js"],"component---src-pages-index-js":["styles.379f2aec5aa6ee65c9e1.css","styles-407fe62976dc5310c43e.js","component---src-pages-index-js-5edc4f3dc8203913b1fc.js"]}}